migration_engine/__init__.py
migration_engine/diff_checker.py
migration_engine/migration_creator.py
migration_engine/model_loader.py
migrations/__init__.py
models/__init__.py
models/task_config.py
utils/__init__.py
utils/decorators.py
umigrator-0.0.2.dist-info/METADATA
umigrator-0.0.2.dist-info/WHEEL
umigrator-0.0.2.dist-info/top_level.txt
umigrator-0.0.2.dist-info/RECORD
